measureunit/__init__.py
measureunit/units.py
measureunit/version.py
measureunit/.src/__init__.py
measureunit/.src/__pycache__/__init__.cpython-311.pyc
measureunit/.src/__pycache__/units.cpython-311.pyc
measureunit/.src/__pycache__/version.cpython-311.pyc
measureunit/.src/test/test_units.py
measureunit/__pycache__/__init__.cpython-311.pyc
measureunit/__pycache__/units.cpython-311.pyc
measureunit/__pycache__/version.cpython-311.pyc
measureunit-0.0.2.post0.dist-info/LICENSE.txt
measureunit-0.0.2.post0.dist-info/METADATA
measureunit-0.0.2.post0.dist-info/WHEEL
measureunit-0.0.2.post0.dist-info/top_level.txt
measureunit-0.0.2.post0.dist-info/RECORD
