Metadata-Version: 2.1
Name: measureunit
Version: 0.0.2.post0
Summary: A Python library of the measurement conversion
Home-page: https://github.com/v-danh/measureunit
Author: v.d.anh
Author-email: vdanhvt2000@gmail.com
License: MIT
Keywords: measureunit,conversion
Classifier: License :: OSI Approved :: MIT License
Classifier: Programming Language :: Python :: 3
Classifier: Operating System :: OS Independent
Requires-Python: >=3
License-File: LICENSE.txt
Provides-Extra: dev
Requires-Dist: pytest >=7.0 ; extra == 'dev'
Requires-Dist: twine >=4.0.2 ; extra == 'dev'
